pluginFecha/__init__.py
pluginFecha/conversion.py
mi_plugin_de_fechas-0.1.0.dist-info/METADATA
mi_plugin_de_fechas-0.1.0.dist-info/WHEEL
mi_plugin_de_fechas-0.1.0.dist-info/top_level.txt
mi_plugin_de_fechas-0.1.0.dist-info/RECORD
